{"resultCode":3,"messageKey":"SUCCESS","returnObject":{"manageColumnsConfig":{"totalColumnCount":9,"columnValueObjects":[{"columnName":"USER_ID","columnDispNameKey":"user.userId","columnId":"23","columnOrder":1,"isVisible":true},{"columnName":"MIDDLE_NM","columnDispNameKey":"user.middleName","columnId":"18","columnOrder":2,"isVisible":true},{"columnName":"MOBILE_PHONE","columnDispNameKey":"user.mobilePhone","columnId":"22","columnOrder":3,"isVisible":true},{"columnName":"PRIMARY_PHONE","columnDispNameKey":"user.primaryPhone","columnId":"21","columnOrder":4,"isVisible":true},{"columnName":"USER_EMAIL","columnDispNameKey":"user.userEmail","columnId":"20","columnOrder":5,"isVisible":true},{"columnName":"USER_STATUS_CODE","columnDispNameKey":"user.userStatusCode","columnId":"24","columnOrder":6,"isVisible":true},{"columnName":"SITE","columnDispNameKey":"config.site","columnId":"139","columnOrder":7,"isVisible":true},{"columnName":"FIRST_NM","columnDispNameKey":"user.firstName","columnId":"17","columnOrder":8,"isVisible":true},{"columnName":"LAST_NM","columnDispNameKey":"user.lastName","columnId":"19","columnOrder":0,"isVisible":false}],"selectedRecords":[],"isCreateAction":true}},"responseDetail":{"warningDetail":[],"validationDetail":[],"successDetail":[{"message":"Success","code":"300000005"}]}}