{"resultCode":3,"messageKey":"SUCCESS","returnObject":{"presavedFilters":[{"filterId":1000000453393,"filterTitle":"11"},{"filterId":1000000453394,"filterTitle":"111"},{"filterId":1000000316437,"filterTitle":"W"},{"filterId":1000000316438,"filterTitle":"WW"},{"filterId":1000000196567,"filterTitle":"a"},{"filterId":1000000385109,"filterTitle":"aa"},{"filterId":1000000196564,"filterTitle":"ddd"},{"filterId":1000000266368,"filterTitle":"ed"},{"filterId":1000000266369,"filterTitle":"edd"},{"filterId":1000000265983,"filterTitle":"xyz"}]},"responseDetail":{"warningDetail":[],"validationDetail":[],"successDetail":[{"message":"Success","code":"300000011"}]}}